blockeng_lasertune/__init__.py
blockeng_lasertune/blkqcl.py
blockeng_lasertune-0.0.1.dist-info/METADATA
blockeng_lasertune-0.0.1.dist-info/WHEEL
blockeng_lasertune-0.0.1.dist-info/licenses/LICENSE
blockeng_lasertune-0.0.1.dist-info/RECORD
