Metadata-Version: 2.3
Name: blockeng-lasertune
Version: 0.0.1
Summary: A Python API for the Block Engineering LaserTune Widely Table QCL software development kit (SDK).
Project-URL: Homepage, https://github.com/houlihaj/blockeng-lasertune
Project-URL: Issues, https://github.com/houlihaj/blockeng-lasertune/issues
Author-email: John Houlihan <houlihaj@uci.edu>
License-File: LICENSE
Classifier: License :: OSI Approved :: MIT License
Classifier: Operating System :: Microsoft :: Windows
Classifier: Programming Language :: Python :: 3
Classifier: Programming Language :: Python :: 3.9
Classifier: Programming Language :: Python :: 3.10
Classifier: Programming Language :: Python :: 3.11
Requires-Python: >=3.9
